<?xml version="1.0" encoding="UTF-8"?>
<addon id="skin.Big-cirrus.Extended" version="2.1.2" name="Big-Cirrus.Extended" provider-name="Eraser (eraser1981@gmail.com)">
	<requires>
		<import addon="xbmc.gui" version="4.0.0"/>
		<import addon="service.skin.widgets" version="0.0.2"/>
		<import addon="script.favourites" version="4.0.7"/>
	</requires>
	<extension
		point="xbmc.gui.skin"
		defaultthemename="textures.xbt"
		debugging="false"
		effectslowdown="0.75">
		<res width="1280" height="720" aspect="16:9" default="true" folder="720p" />
	</extension>
	<extension point="xbmc.addon.metadata">
		<platform>all</platform>
		<summary lang="en">Big-Cirrus.Extended skin by Eraser (Based on Big-Cirrus skin by GMib)</summary>
		<summary lang="ru">Big-Cirrus.Extended скин от Eraser (В основе скин Big-Cirrus от GMib)</summary>
		<description lang="en">Big-Cirrus.Extended is a modded version of GMib's Big-Cirrus skin modded. Cirrus is a lightweight skin which has a focus on speed, ease of use and ease of navigation. It also uses TV logos, cleararts, and cdart if you want them.</description>
		<description lang="ru">Big-Cirrus.Extended - мод скина Big-Cirrus.</description>
	</extension>
</addon>
